{
  "Id": "6d37d75c-0015-4aa9-8176-97b750da0265",
  "OriginalId": "42",
  "Name": "Героизм [Heroism]",
  "Hold": false,
  "HoldTime": "0001-01-01T00:00:00",
  "ReplaceOriginal": true,
  "OrigName": "Heroism",
  "Level": 1,
  "School": "6",
  "Time": "1 действие",
  "Range": "Касание",
  "V": true,
  "S": true,
  "ReqSee": false,
  "M": false,
  "ComponentText": "",
  "Duration": "Концентрация, вплоть до 1 минуты",
  "Classes": "12|16",
  "HtmlText": "Существо по вашему выбору, которое вы касаетесь, наполняется смелостью. Пока заклинание действует, существо становится невосприимчивым к состоянию испуга и получает Временные хиты, равные вашему модификатору заклинательной характеристики ([mod]), в начале каждого своего хода. На больших уровнях: Вы можете выбрать одно дополнительное существо за каждый уровень ячейки заклинаний выше 1."
}