{
  "Id": "e9491886-1832-4ff6-ba7a-3c2d131ffbbd",
  "OriginalId": "477",
  "Name": "Ледяной кинжал [Ice Knife]",
  "Hold": false,
  "HoldTime": "0001-01-01T00:00:00",
  "ReplaceOriginal": true,
  "OrigName": "Ice Knife",
  "Level": 1,
  "School": "2",
  "Time": "1 действие",
  "Range": "60 футов",
  "V": false,
  "S": true,
  "ReqSee": false,
  "M": false,
  "ComponentText": "капля воды или кусочек льда",
  "Duration": "Мгновенная",
  "Classes": "19|21|22",
  "HtmlText": "Вы создаёте осколок льда и бросаете его в одно существо в пределах дистанции. Совершите дальнобойную атаку заклинанием по цели. При попадании цель получает 1к10 колющего урона. После этого, вне зависимости от попадания или промаха, осколок взрывается. Цель и каждое существо в пределах 5 фт от неё должны совершить Спасбросок Ловкости, иначе получат 2к6 урона холодом. На более высоких уровнях. Урон холодом увеличивается на 1к6 за каждый уровень ячейки заклинаний выше 1."
}