{
  "Id": "9ae791d5-e4d6-4a25-9f00-9f0c879db3fc",
  "OriginalId": "180",
  "Name": "Нашествие насекомых [Insect plague]",
  "Hold": false,
  "HoldTime": "0001-01-01T00:00:00",
  "ReplaceOriginal": true,
  "OrigName": "Insect plague",
  "Level": 5,
  "School": "2",
  "Time": "1 действие",
  "Range": "300 футов",
  "V": true,
  "S": true,
  "ReqSee": false,
  "M": true,
  "ComponentText": "саранча",
  "Duration": "Концентрация, до 10 минут",
  "Classes": "13|19|22",
  "HtmlText": "Рой саранчи заполняет сферу радиусом <ft cell=5>20</ft> с центром в точке, которую вы выбираете в пределах дистанции. Сфера остаётся на время длительности заклинания, и её область становится <st id=\"light_dis\" box=0 hidden=0 name=\"слегка заслонённой\" t=0 modes=\"5;;0;;0;0;0;;0;0;1;0;;0;;-1;;0;0;0;0;0;;a13;;0;0;0\" ><rtb i=4></rtb><rtb i=1></rtb><rtb i=2></rtb><rtb i=3></rtb></st> и <st id=\"a97a5776-0c26-447e-b131-0b2d9f50a065\" box=0 hidden=0 name=\"труднопроходимой местностью\" t=0 modes=\"16;;0;-15;0;0;0;Пешком;0;0;1;0;;0;;-1;;0;0;0;0;0;;;;0;0;0\" ><rtb i=4></rtb><rtb i=1></rtb><rtb i=2></rtb><rtb i=3></rtb></st>.\r\nКогда рой появляется, то каждое существо в его пределах совершает <ch new=1 p=0 clear=0 h=0 ps=0 psm=0 prof=0 text=\"Спасбросок Телосложения\" difLevel=\"1|4\" mod=\"0\" customValue=\"[dc]\" id=\"s3\">Спасбросок Телосложения СЛ [dc]</ch>, получая <dice dmgType=\"12\" name=\"4к10\">4к10</dice> колющего урона при неудачном спасброске или половину этого урона при успешном. Существо также совершает этот спасбросок, когда впервые за ход входит в область действия заклинания или заканчивает там свой ход. Существо совершает этот спасбросок только один раз за ход.\r\n<zag size=\"14\" s=1 >На больших уровнях:</zag>  Урон увеличивается на <dice dmgType=\"12\" name=\"1к10\">1к10</dice> за каждый уровень ячейки выше 5-го."
}