{
  "Id": "384dc6cb-bc65-49be-8ffc-134ba7a0d209",
  "OriginalId": "283",
  "Name": "Проекция [Project image]",
  "Hold": false,
  "HoldTime": "0001-01-01T00:00:00",
  "ReplaceOriginal": true,
  "OrigName": "Project image",
  "Level": 7,
  "School": "3",
  "Time": "1 действие",
  "Range": "500 миль",
  "V": true,
  "S": true,
  "ReqSee": true,
  "M": true,
  "ComponentText": "изображающая вас статуэтка стоимостью 5+ зм",
  "Duration": " Концентрация, до 1 дня",
  "Classes": "12|21",
  "HtmlText": "Вы создаёте иллюзорную копию себя, которая существует в течение длительности заклинания. Копия может появиться в любом месте в пределах дистанции, которое вы ранее видели, независимо от преград. Иллюзия выглядит и звучит как вы, но она нематериальна. Если иллюзия получает урон, то она исчезает и заклинание заканчивается. Вы можете видеть через глаза иллюзии и слышать через её уши, как будто вы находитесь в её пространстве. Действием Магия вы можете переместить её на 60 фт и заставить её жестикулировать, говорить и вести себя так, как вы хотите. Она идеально копирует ваши манеры. Физическое взаимодействие с копией показывает, что это иллюзия, так как вещи могут проходить через неё. Существо, использующее Действие изучение для анализа образа, может определить, что это иллюзия, сделав успешную проверку Интеллекта (Анализ) против вашего Сл. спасброска заклинания. Если существо распознает иллюзию, то оно может видеть через образ, а любой звук, который она издаёт, кажется ему приглушённым."
}