{
  "Id": "e9059841-50d8-45ff-bced-0540c616fc25",
  "OriginalId": "299",
  "Name": "Распад [Disintegrate]",
  "Hold": false,
  "HoldTime": "0001-01-01T00:00:00",
  "ReplaceOriginal": true,
  "OrigName": "Disintegrate",
  "Level": 6,
  "School": "7",
  "Time": "1 действие",
  "Range": "60 футов",
  "V": true,
  "S": true,
  "ReqSee": true,
  "M": true,
  "ComponentText": "магнетит и прах",
  "Duration": "Мгновенная",
  "Classes": "19|21",
  "HtmlText": "Вы выпускаете зелёный луч в цель, которую видите в пределах дистанции. Целью может быть существо, немагический предмет или творение из магической силы, например, стена, созданная заклинанием Силовая стена [Wall of force]. Существо, на которое направлено это заклинание, совершает Спасбросок Ловкости. При провале, цель получает 10к6+40 урона силовым полем. Если этот урон снижает хиты цели до 0, то цель и также всё, что она несёт и носит, кроме магических предметов, превращается в кучку мелкого серого праха. Цель может быть возвращена к жизни только заклинаниями Истинное воскрешение [True resurrection] или Исполнение желаний [Wish]. Это заклинание автоматически уничтожает не магический предмет Большого размера или меньший или творение из магической силы. Если такой целью является объект огромного размера или больше, то это заклинание уничтожает 10 фт куб его части. На больших уровнях: Урон увеличивается на 3к6 за каждый уровень ячейки заклинания выше 6."
}