{
  "Id": "e262bb57-30e6-41a9-8112-5db674b5515f",
  "OriginalId": "322",
  "Name": "Слово силы Смерть [Power word kill]",
  "Hold": false,
  "HoldTime": "0001-01-01T00:00:00",
  "ReplaceOriginal": true,
  "OrigName": "Power word kill",
  "Level": 9,
  "School": "6",
  "Time": "1 действие",
  "Range": "60 футов",
  "V": true,
  "S": false,
  "ReqSee": true,
  "M": false,
  "ComponentText": "",
  "Duration": "Мгновенно",
  "Classes": "12|21|20|19",
  "HtmlText": "Вы заставляете одно существо, которое видите в пределах дистанции, умереть. Если у цели <dice dmgType=\"31\" name=\"100\">100</dice> хитов или меньше, то она умирает. В противном случае она получает <dice dmgType=\"22\" name=\"12к12\">12к12</dice> урона психической энергией."
}