{
  "Id": "703f561d-cc3a-4222-ab8a-025211b695d3",
  "OriginalId": "345",
  "Name": "Телепатия [Telepathy]",
  "Hold": false,
  "HoldTime": "0001-01-01T00:00:00",
  "ReplaceOriginal": true,
  "OrigName": "Telepathy",
  "Level": 8,
  "School": "8",
  "Time": "1 действие",
  "Range": "Без ограничений",
  "V": true,
  "S": true,
  "ReqSee": false,
  "M": true,
  "ComponentText": "пара связанных серебряных колец",
  "Duration": "24 часа",
  "Classes": "21",
  "HtmlText": "Вы создаёте телепатическую связь между собой и согласным существом, с которым вы знакомы. Существо может находиться в любом месте на том же плане, что и вы. Заклинание прекращается, если вы или цель окажетесь на разных планах.\r\nДо окончания действия заклинания вы и цель можете мгновенно делиться словами, изображениями, звуками и другими сенсорными сообщениями через связь, и цель узнаёт вас как существо, с которым она общается. Заклинание позволяет существу понимать смысл ваших слов и любых сенсорных сообщений, которые вы ему отправляете."
}